fastapi_storages/__init__.py
fastapi_storages/base.py
fastapi_storages/exceptions.py
fastapi_storages/filesystem.py
fastapi_storages/s3.py
fastapi_storages/utils.py
fastapi_storages/integrations/__init__.py
fastapi_storages/integrations/sqlalchemy.py
fastapi_storages-0.2.1.dist-info/METADATA
fastapi_storages-0.2.1.dist-info/WHEEL
fastapi_storages-0.2.1.dist-info/licenses/LICENSE.txt
fastapi_storages-0.2.1.dist-info/RECORD
