Metadata-Version: 2.1
Name: fastapi-storages
Version: 0.2.1
Summary: FastAPI Storages
Project-URL: Documentation, https://github.com/aminalaee/fastapi-storages#readme
Project-URL: Issues, https://github.com/aminalaee/fastapi-storages/issues
Project-URL: Source, https://github.com/aminalaee/fastapi-storages
Author-email: Amin Alaee <me@aminalaee.dev>
License-Expression: MIT
License-File: LICENSE.txt
Keywords: django,fastapi,orm,sqlalchemy
Classifier: Development Status :: 4 - Beta
Classifier: Programming Language :: Python
Classifier: Programming Language :: Python :: 3.8
Classifier: Programming Language :: Python :: 3.9
Classifier: Programming Language :: Python :: 3.10
Classifier: Programming Language :: Python :: 3.11
Classifier: Programming Language :: Python :: 3.12
Classifier: Topic :: Database
Classifier: Topic :: Database :: Database Engines/Servers
Classifier: Topic :: Internet
Classifier: Topic :: Internet :: WWW/HTTP
Classifier: Topic :: Internet :: WWW/HTTP :: HTTP Servers
Classifier: Typing :: Typed
Requires-Python: >=3.8
Requires-Dist: boto3~=1.25
Provides-Extra: full
Requires-Dist: pillow~=9.4; extra == 'full'
Requires-Dist: sqlalchemy>=1.4; extra == 'full'
